[
    {
      "productId": "6586ff8defea81613b1659da",
      "paidStatus": false,
      "orderStatus": "pending",
      "transactionId": "6599364ec663281d68a0f43b",
      "cusName": "Jahid Hasan",
      "cusPhone": "80188416724",
      "cusEmail": "apurbahasanj@gmail.com",
      "cusAdd": "Begumganj",
      "cusLocation": "insideDhaka",
      "couponCode": "",
      "color": "yellowgreen",
      "size": "M",
      "quantity": 2,
      "totalAmount": 1140,
      "paymentMethod": "COD",
      "createdAt": "Saturday, January 6, 2024 at 5:15:25 PM"
    },
    {
      "productId": "6585cbb2a84c0d0d3926bd42",
      "paidStatus": false,
      "orderStatus": "pending",
      "transactionId": "65993669c663281d68a0f43d",
      "cusName": "Jahid Hasan",
      "cusPhone": "80188416724",
      "cusEmail": "apurbahasanj@gmail.com",
      "cusAdd": "Begumganj",
      "cusLocation": "insideDhaka",
      "couponCode": "",
      "color": "red",
      "size": "XXL",
      "quantity": 2,
      "totalAmount": 1040,
      "paymentMethod": "COD",
      "createdAt": "Saturday, January 6, 2024 at 5:15:51 PM"
    },
    {
      "productId": "6585cbb2a84c0d0d3926bd4c",
      "paidStatus": false,
      "orderStatus": "rejected",
      "transactionId": "65993680c663281d68a0f43f",
      "cusName": "Jahid Hasan",
      "cusPhone": "80188416724",
      "cusEmail": "apurbahasanj@gmail.com",
      "cusAdd": "Begumganj",
      "cusLocation": "insideDhaka",
      "couponCode": "",
      "color": "black",
      "size": "M",
      "quantity": 2,
      "totalAmount": 1240,
      "paymentMethod": "COD",
      "createdAt": "Saturday, January 6, 2024 at 5:16:15 PM"
    },
    {
      "productId": "6586ff8defea81613b1659da",
      "paidStatus": true,
      "orderStatus": "pending",
      "transactionId": "659991388b0658f4eeaaaacf",
      "cusName": "Jahid Hasan",
      "cusPhone": "80188416724",
      "cusEmail": "apurbahasanj@gmail.com",
      "cusAdd": "Begumganj",
      "cusLocation": "insideDhaka",
      "couponCode": "",
      "color": "yellowgreen",
      "size": "M",
      "quantity": 2,
      "totalAmount": 1140,
      "paymentMethod": "Online",
      "createdAt": "Saturday, January 6, 2024 at 11:43:18 PM"
    },
    {
      "productId": "6586ff8defea81613b1659da",
      "paidStatus": false,
      "orderStatus": "confirmed",
      "transactionId": "6599ab08404316292a466349",
      "cusName": "Jahid Hasan",
      "cusPhone": "80188416724",
      "cusEmail": "apurbahasanj@gmail.com",
      "cusAdd": "Begumganj",
      "cusLocation": "insideDhaka",
      "couponCode": "Z20",
      "orderNote": "nothing",
      "color": "yellowgreen",
      "size": "L",
      "quantity": 2,
      "totalAmount": 920,
      "paymentMethod": "COD",
      "createdAt": "Sunday, January 7, 2024 at 1:33:21 AM"
    }
  ]
  